rickcommons/__init__.py
rickcommons/server.py
rickcommons/test.py
rickcommons-1.1.0.dist-info/METADATA
rickcommons-1.1.0.dist-info/WHEEL
rickcommons-1.1.0.dist-info/entry_points.txt
rickcommons-1.1.0.dist-info/RECORD
