Metadata-Version: 2.4
Name: rickcommons
Version: 1.1.0
Summary: 一个python redis 的简易分布式消息实现
Author-email: LH <276069869@qq.com>
License: MIT
Requires-Python: >=3.8.6
Requires-Dist: redis>=6.1.1
